griffon_client/__init__.py
griffon_client/connect.py
griffon_client-0.2.4.dist-info/LICENSE
griffon_client-0.2.4.dist-info/WHEEL
griffon_client-0.2.4.dist-info/METADATA
griffon_client-0.2.4.dist-info/RECORD
