Metadata-Version: 2.1
Name: griffon-client
Version: 0.2.4
Summary: A message queue for connecting workflows
License: MIT
Author: August Brenner
Author-email: augustbrenner@gmail.com
Requires-Python: >=3.8,<4.0
Classifier: License :: OSI Approved :: MIT License
Classifier: Programming Language :: Python :: 3
Classifier: Programming Language :: Python :: 3.8
Requires-Dist: python-socketio[client] (>=4.6.0,<5.0.0)
